README.rst
setup.py
EyeTracker.egg-info/PKG-INFO
EyeTracker.egg-info/SOURCES.txt
EyeTracker.egg-info/dependency_links.txt
EyeTracker.egg-info/top_level.txt
PyET/PyETCore.py
PyET/__init__.py
PyET/__main__.py
PyET/main_ui.py
PyET/settings.py
PyET/classes/__init__.py
PyET/classes/enhanced_cam.py
PyET/classes/frame_updater.py
PyET/classes/recorder.py
PyET/tests/__init__.py
PyET/tests/check_camera.py
PyET/tests/check_record.py
PyET/ui/__init__.py
PyET/ui/editor_dialog.py
PyET/ui/main_window.py
PyET/ui/secondary_window.py